linksiren/__init__.py
linksiren/__main__.py
linksiren/arg_parser.py
linksiren/impure_functions.py
linksiren/logging_config.py
linksiren/mode_handlers.py
linksiren/pure_functions.py
linksiren/target.py
linksiren/template.library-ms
linksiren/template.lnk
linksiren/template.searchConnector-ms
linksiren/template.url
linksiren-0.0.4.dist-info/LICENSE
linksiren-0.0.4.dist-info/METADATA
linksiren-0.0.4.dist-info/WHEEL
linksiren-0.0.4.dist-info/entry_points.txt
linksiren-0.0.4.dist-info/top_level.txt
linksiren-0.0.4.dist-info/RECORD
