Metadata-Version: 2.2
Name: linksiren
Version: 0.0.4
Summary: Generation, targeted deployment, and scalable cleanup for files that coerce Windows authentication.
Author: George Hamilton
License: BSD 3-Clause License
Project-URL: Homepage, https://github.com/gjhami/LinkSiren
Project-URL: Issues, https://github.com/gjhami/LinkSiren/issues
Keywords: coerce,pentest,windows,authentication,coercion
Classifier: Operating System :: OS Independent
Classifier: Topic :: Security
Classifier: Programming Language :: Python :: 3
Requires-Python: >=3.9
License-File: LICENSE
Requires-Dist: impacket>=0.11.0
Requires-Dist: tqdm>=4.67.1
Provides-Extra: dev
Requires-Dist: black; extra == "dev"
Requires-Dist: bumpver; extra == "dev"
Requires-Dist: isort; extra == "dev"
Requires-Dist: pip-tools; extra == "dev"
Requires-Dist: pytest; extra == "dev"
Requires-Dist: coverage; extra == "dev"
Requires-Dist: ruff; extra == "dev"
